yellow_changer_api/__init__.py
yellow_changer_api/exceptions.py
yellow_changer_api/yellow_changer.py
yellowchangerapi-1.0.4.dist-info/METADATA
yellowchangerapi-1.0.4.dist-info/WHEEL
yellowchangerapi-1.0.4.dist-info/top_level.txt
yellowchangerapi-1.0.4.dist-info/RECORD
