Metadata-Version: 2.1
Name: yellowchangerapi
Version: 1.0.4
Summary: A Python library for interacting with the YellowChanger service API.
Home-page: https://github.com/yellowfluf/YellowChangerAPI
Author: Fluf
Author-email: support@yellowchanger.com
Project-URL: Bug Reports, https://github.com/yellowfluf/YellowChangerAPI/issues
Project-URL: Source, https://github.com/yellowfluf/YellowChangerAPI/tree/main
Classifier: Programming Language :: Python :: 3
Classifier: License :: OSI Approved :: MIT License
Classifier: Operating System :: OS Independent
Requires-Python: >=3.9
Requires-Dist: requests
